[
  {
    "id": 4,
    "name": "ADMIN",
    "description": "PERFIL GERENCIADOR",
    "permissions": {
      "almoxarifado": true,
      "chamados": true,
      "comercial": true,
      "compras": true,
      "desenvolvimento": true,
      "marketing": true,
      "projetos": true,
      "rh": true,
      "suporte": true,
      "tecnologia": true
    },
    "isDefault": true,
    "createdAt": 1770160822191,
    "updatedAt": 1771986812339
  },
  {
    "id": 150001,
    "name": "Financeiro ",
    "description": "Usuarios",
    "permissions": {
      "almoxarifado": true,
      "chamados": true,
      "desenvolvimento": true,
      "marketing": false,
      "projetos": false,
      "rh": false,
      "suporte": true,
      "tecnologia": false
    },
    "isDefault": false,
    "createdAt": 1770244407982,
    "updatedAt": 1772108165645
  },
  {
    "id": 150022,
    "name": "Compras",
    "description": "",
    "permissions": {
      "almoxarifado": true,
      "chamados": true,
      "comercial": false,
      "compras": false,
      "desenvolvimento": true,
      "marketing": false,
      "projetos": false,
      "rh": false,
      "suporte": true,
      "tecnologia": false
    },
    "isDefault": false,
    "createdAt": 1770252829737,
    "updatedAt": 1772108110826
  },
  {
    "id": 240001,
    "name": "Controladoria",
    "description": "",
    "permissions": {
      "almoxarifado": true,
      "chamados": true,
      "compras": false,
      "desenvolvimento": true,
      "marketing": false,
      "projetos": false,
      "rh": false,
      "suporte": true,
      "tecnologia": false
    },
    "isDefault": false,
    "createdAt": 1770661461652,
    "updatedAt": 1772108134049
  },
  {
    "id": 300001,
    "name": "Comercial",
    "description": "",
    "permissions": {
      "almoxarifado": true,
      "chamados": true,
      "comercial": false,
      "compras": false,
      "desenvolvimento": true,
      "marketing": false,
      "projetos": false,
      "rh": false,
      "suporte": true,
      "tecnologia": false
    },
    "isDefault": false,
    "createdAt": 1770922468551,
    "updatedAt": 1772108124582
  },
  {
    "id": 330001,
    "name": "Logistica",
    "description": "",
    "permissions": {
      "almoxarifado": true,
      "chamados": true,
      "compras": false,
      "desenvolvimento": false,
      "marketing": false,
      "projetos": false,
      "rh": false,
      "suporte": true,
      "tecnologia": false
    },
    "isDefault": false,
    "createdAt": 1770925040950,
    "updatedAt": 1772108185447
  },
  {
    "id": 360007,
    "name": "RH/DP",
    "description": "",
    "permissions": {
      "almoxarifado": true,
      "chamados": true,
      "compras": false,
      "desenvolvimento": true,
      "marketing": false,
      "projetos": false,
      "rh": false,
      "suporte": true,
      "tecnologia": false
    },
    "isDefault": false,
    "createdAt": 1770985333375,
    "updatedAt": 1772108173494
  },
  {
    "id": 660001,
    "name": "Diretoria",
    "description": null,
    "permissions": {
      "almoxarifado": true,
      "comercial": false,
      "desenvolvimento": true,
      "suporte": true
    },
    "isDefault": false,
    "createdAt": 1771986716672,
    "updatedAt": 1771986716672
  }
]